[
  {
    "username": "test",
    "timeNow": "2024-04-17T13:09:32.370Z"
  },
  {
    "username": "test",
    "timeNow": "2024-04-17T13:11:04.049Z"
  },
  {
    "username": "test",
    "timeNow": "2024-04-17T13:12:55.794Z"
  },
  {
    "username": "test",
    "timeNow": "2024-04-17T13:13:31.327Z"
  },
  {
    "username": "test",
    "timeNow": "2024-04-17T13:53:36.089Z"
  },
  {
    "username": "test",
    "timeNow": "2024-04-17T17:05:22.099Z"
  },
  {
    "username": "test",
    "timeNow": "2024-04-17T17:06:50.888Z"
  },
  {
    "username": "test",
    "timeNow": "2024-04-17T17:07:58.597Z"
  },
  {
    "username": "test",
    "timeNow": "2024-04-17T17:08:39.863Z"
  },
  {
    "username": "test",
    "timeNow": "2024-04-18T18:28:46.896Z"
  },
  {
    "username": "test",
    "timeNow": "2024-04-18T18:28:51.948Z"
  },
  {
    "username": "test",
    "timeNow": "2024-04-18T18:53:50.784Z"
  },
  {
    "username": "test",
    "timeNow": "2024-04-19T14:12:18.225Z"
  }
]